{"width":512,"imagePath":"towe_animation_DB_tex.png","height":256,"name":"towe_animation_DB","SubTexture":[{"width":36,"y":120,"height":90,"name":"Towe_animation/braco2_2","x":461},{"width":36,"y":174,"height":73,"name":"Towe_animation/braco2","x":319},{"width":66,"y":1,"height":95,"name":"Towe_animation/busto","x":251},{"width":52,"y":120,"height":111,"name":"Towe_animation/perna2_","x":363},{"width":67,"y":1,"height":176,"name":"Towe_animation/perna2_1","x":1},{"width":75,"y":104,"height":106,"name":"Towe_animation/bermuda","x":242},{"width":42,"y":1,"height":171,"name":"Towe_animation/perna1_frente","x":319},{"width":68,"y":1,"height":173,"name":"Towe_animation/perna1_lado","x":70},{"width":59,"y":1,"height":117,"name":"Towe_animation/perna1","x":363},{"width":22,"y":176,"height":53,"name":"Towe_animation/cabelo2","x":70},{"width":100,"y":104,"height":100,"name":"Towe_animation/cabeca","x":140},{"width":46,"y":212,"height":23,"name":"Towe_animation/olhos1_fechado","x":417},{"width":46,"y":95,"height":23,"name":"Towe_animation/olhos1","x":424},{"width":46,"y":212,"height":23,"name":"Towe_animation/olhos1_Copy","x":465},{"width":109,"y":1,"height":101,"name":"Towe_animation/cabelo1","x":140},{"width":31,"y":1,"height":92,"name":"Towe_animation/braco1_2","x":424},{"width":42,"y":120,"height":84,"name":"Towe_animation/braco1","x":417}]}